youless_api/__init__.py
youless_api/const.py
youless_api/youless_sensor.py
youless_api/device/__init__.py
youless_api/gateway/__init__.py
youless_api/test/__init__.py
youless_api/test/test_api.py
youless_api/test/test_gateway_enelogic.py
youless_api/test/test_gateway_generic.py
youless_api/test/test_youless_sensor.py
youless_api-2.1.2.dist-info/LICENSE
youless_api-2.1.2.dist-info/METADATA
youless_api-2.1.2.dist-info/WHEEL
youless_api-2.1.2.dist-info/top_level.txt
youless_api-2.1.2.dist-info/RECORD
