Metadata-Version: 2.1
Name: youless_api
Version: 2.1.2
Summary: A bridge for python to the YouLess sensor
Home-page: https://github.com/gjong/youless-python-bridge
Author: G. Jongerius
License: MIT
License-File: LICENSE
